README.md
setup.py
pynvn/__init__.py
pynvn.egg-info/PKG-INFO
pynvn.egg-info/SOURCES.txt
pynvn.egg-info/dependency_links.txt
pynvn.egg-info/requires.txt
pynvn.egg-info/top_level.txt
pynvn/authkey/__init__.py
pynvn/autoscrollbar/__init__.py
pynvn/autoscrollbar/autoscrbar.py
pynvn/caculate/__init__.py
pynvn/caculate/area.py
pynvn/caculate/cacul_cavas.py
pynvn/caculate/coord_point.py
pynvn/caculate/ratio.py
pynvn/cavas_dim/__init__.py
pynvn/cavas_dim/cavas_dim.py
pynvn/cavas_drawing/__init__.py
pynvn/cavas_drawing/buttondr.py
pynvn/cavas_drawing/draw.py
pynvn/cavas_write/__init__.py
pynvn/cavas_write/writetext.py
pynvn/cavaszm/__init__.py
pynvn/cavaszm/cavaszm.py
pynvn/check/Hstr_StrRetrFile_1.py
pynvn/check/__init__.py
pynvn/check/list.py
pynvn/checklb/__init__.py
pynvn/checklb/checkb.py
pynvn/crypt/__init__.py
pynvn/csv/__init__.py
pynvn/csv/rcsv.py
pynvn/csv/tocsv.py
pynvn/csv/todict.py
pynvn/csv/tolist.py
pynvn/ctn/__init__.py
pynvn/data/__init__.py
pynvn/data/filename.py
pynvn/data/hdata.py
pynvn/dict/__init__.py
pynvn/dict/createdict.py
pynvn/dict/csv.py
pynvn/error/__init__.py
pynvn/error/cerror.py
pynvn/excel/Fill_formula.py
pynvn/excel/__init__.py
pynvn/excel/convertexelltocsv.py
pynvn/excel/copy_move_paste.py
pynvn/excel/copyexcel.py
pynvn/excel/copypasteexell.py
pynvn/excel/crelistadict.py
pynvn/excel/del_row.py
pynvn/excel/delete.py
pynvn/excel/fexcell.py
pynvn/excel/fformulaexcel.py
pynvn/excel/fomulas.py
pynvn/excel/hdata.py
pynvn/excel/hexcel.py
pynvn/excel/hrow.py
pynvn/excel/lexcel.py
pynvn/excel/list.py
pynvn/excel/path.py
pynvn/excel/toexcel.py
pynvn/excel/write.py
pynvn/excel/exception/__init__.py
pynvn/excel/openpyxl/__init__.py
pynvn/excel/rows/__init__.py
pynvn/folder/__init__.py
pynvn/folder/list.py
pynvn/gdrive/__init__.py
pynvn/gdrive/sheet.py
pynvn/ggdrive/__init__.py
pynvn/ggdrive/auth.py
pynvn/hlstr/__init__.py
pynvn/hlstr/hlstr.py
pynvn/iter/__init__.py
pynvn/list/__init__.py
pynvn/list/flist.py
pynvn/list/str.py
pynvn/list/tocsv.py
pynvn/list/twolist.py
pynvn/login/__init__.py
pynvn/login/atadlogin.py
pynvn/mc_id/__init__.py
pynvn/nsew/__init__.py
pynvn/nsew/nsew.py
